ai_kernel/__init__.py
ai_kernel/config.py
ai_kernel/core.py
ai_kernel/db.py
ai_kernel/main.py
ai_kernel/session.py
ktml_agent-0.1.3.dist-info/METADATA
ktml_agent-0.1.3.dist-info/WHEEL
ktml_agent-0.1.3.dist-info/entry_points.txt
ktml_agent-0.1.3.dist-info/top_level.txt
ktml_agent-0.1.3.dist-info/RECORD
