Metadata-Version: 2.4
Name: ktml-agent
Version: 0.1.3
Summary: AI Terminal Agent
Author-email: Avime <avime@example.com>
Classifier: Programming Language :: Python :: 3
Classifier: License :: OSI Approved :: MIT License
Classifier: Operating System :: OS Independent
Requires-Python: >=3.8
